setup.py
scoped/__init__.py
scoped/models.py
scoped.egg-info/PKG-INFO
scoped.egg-info/SOURCES.txt
scoped.egg-info/dependency_links.txt
scoped.egg-info/requires.txt
scoped.egg-info/top_level.txt
scoped.egg-info/zip-safe
scoped/tests/__init__.py
scoped/tests/models.py