Metadata-Version: 1.0
Name: scoped
Version: 0.1.0
Summary: easily add scopes to django models
Home-page: UNKNOWN
Author: Viktor Kotseruba
Author-email: barbuzaster@gmail.com
License: MIT
Keywords: django
Platform: UNKNOWN
